pygrt/__init__.py
pygrt/_version.py
pygrt/c_interfaces.py
pygrt/c_structures.py
pygrt/print.py
pygrt/pygrn.py
pygrt/pymod.py
pygrt/signals.py
pygrt/utils.py
pygrt/C_extension/Makefile
pygrt/C_extension/version
pygrt/C_extension/bin/grt
pygrt/C_extension/include/grt.h
pygrt/C_extension/include/grt/common/RT_matrix.h
pygrt/C_extension/include/grt/common/attenuation.h
pygrt/C_extension/include/grt/common/bessel.h
pygrt/C_extension/include/grt/common/checkerror.h
pygrt/C_extension/include/grt/common/colorstr.h
pygrt/C_extension/include/grt/common/const.h
pygrt/C_extension/include/grt/common/coord.h
pygrt/C_extension/include/grt/common/logo.h
pygrt/C_extension/include/grt/common/matrix.h
pygrt/C_extension/include/grt/common/model.h
pygrt/C_extension/include/grt/common/myfftw.h
pygrt/C_extension/include/grt/common/mynetcdf.h
pygrt/C_extension/include/grt/common/progressbar.h
pygrt/C_extension/include/grt/common/prtdbg.h
pygrt/C_extension/include/grt/common/radiation.h
pygrt/C_extension/include/grt/common/sacio.h
pygrt/C_extension/include/grt/common/sacio2.h
pygrt/C_extension/include/grt/common/search.h
pygrt/C_extension/include/grt/common/travt.h
pygrt/C_extension/include/grt/common/util.h
pygrt/C_extension/include/grt/common/version.h
pygrt/C_extension/include/grt/dynamic/grn.h
pygrt/C_extension/include/grt/dynamic/layer.h
pygrt/C_extension/include/grt/dynamic/signals.h
pygrt/C_extension/include/grt/dynamic/source.h
pygrt/C_extension/include/grt/dynamic/syn.h
pygrt/C_extension/include/grt/integral/dcm.h
pygrt/C_extension/include/grt/integral/dwm.h
pygrt/C_extension/include/grt/integral/fim.h
pygrt/C_extension/include/grt/integral/integ_method.h
pygrt/C_extension/include/grt/integral/iostats.h
pygrt/C_extension/include/grt/integral/k_integ.h
pygrt/C_extension/include/grt/integral/kernel.h
pygrt/C_extension/include/grt/integral/ptam.h
pygrt/C_extension/include/grt/integral/quadratic.h
pygrt/C_extension/include/grt/integral/safim.h
pygrt_kit-0.14.0.dist-info/licenses/LICENSE
pygrt_kit-0.14.0.dist-info/METADATA
pygrt_kit-0.14.0.dist-info/WHEEL
pygrt_kit-0.14.0.dist-info/top_level.txt
pygrt_kit-0.14.0.dist-info/RECORD
