Metadata-Version: 2.4
Name: pygrt-kit
Version: 0.14.0
Summary: An Efficient and Integrated Python Package for Computing Synthetic Seismograms in a Layered Half-Space Model
Home-page: https://github.com/Dengda98/PyGRT
Author: Zhu Dengda
Author-email: zhudengda@mail.iggcas.ac.cn
License: GPL-3.0
Project-URL: Documentation, https://pygrt.readthedocs.io/zh-cn/latest/
Project-URL: Source Code, https://github.com/Dengda98/PyGRT
Requires-Python: >=3.6
License-File: LICENSE
Requires-Dist: numpy<2.0,>=1.20
Requires-Dist: scipy>=1.10
Requires-Dist: matplotlib>=3.5
Requires-Dist: obspy>=1.4
Dynamic: author
Dynamic: author-email
Dynamic: description
Dynamic: description-content-type
Dynamic: home-page
Dynamic: license
Dynamic: license-file
Dynamic: project-url
Dynamic: requires-dist
Dynamic: requires-python
Dynamic: summary
